{
  "title": "JavaScript",
  "questions": [
    {
      "question": "Hvað er skrifað út eftir að eftirfarandi kóði er keyrður?\n\nconst items = [1, 2, 3, 4, 5, 6, 7, 8, 9, 10];\n\nconst іtem = items\n  .map((i) => i * 2)\n  .filter(\n    (i) => i < 10\n  )\n  .find((i) => i > 6)\n\n\nconsole.log(item);",
      "answers": [
        {
          "answer": "8",
          "correct": true
        },
        {
          "answer": "[8]",
          "correct": false
        },
        {
          "answer": "Uncaught ReferenceError: item is not defined",
          "correct": false
        },
        {
          "answer": "undefined",
          "correct": false
        }
      ]
    },
    {
      "question": "Þegar við berum saman gildi í JavaScript ættum við alltaf að nota þrjú samasem merki (`===`) því að",
      "answers": [
        {
          "answer": "Þessi samanburður byrjar á að bera saman týpur gilda og kemst því framhjá type coercion sem gerist með samanburð með tveimur samasem merkjum.",
          "correct": true
        },
        {
          "answer": "Við ættum alltaf að nota tvö samasem merki, ekki þrjú því þá byrjum við á að bera saman týpur gilda og komumst þannig framhjá type coercion.",
          "correct": false
        },
        {
          "answer": "Þessi samanburður kemst framhjá truthy og falsy gildum og skilar eingöngu réttum niðurstöðum fyrir primitive gildi.",
          "correct": false
        },
        {
          "answer": "Þessi samanburður nýtir lógíska virkja sem virka aðeins í tvístæðum.",
          "correct": false
        }
      ]
    },
    {
      "question": "Þegar við notum `fetch` í JavaScript ætti ferlið við að sækja gögn að vera",
      "answers": [
        {
          "answer": "Búið til `fetch` request kall sem tilgreinir að minnsta kosti URL; villuathugun á kalli og svari með tilliti til HTTP; gögn sótt í response með villuathugun.",
          "correct": true
        },
        {
          "answer": "Búið til `fetch` request kall sem verður að tilgreina URL, HTTP aðferð og stöðukóða; villuathugun á kalli og svari með tilliti til HTTP; gögn sótt í response með villuathugun.",
          "correct": false
        },
        {
          "answer": "Búið til `fetch` request kall sem tilgreinir að minnsta kosti URL; villuathugun á kalli og svari með tilliti til URL; gögn sótt í response.",
          "correct": false
        },
        {
          "answer": "Búið til `fetch` request kall sem tilgreinir að minnsta kosti URL; villuathugun á kalli og svari með tilliti til HTTP; eingöngu JSON gögn sótt í response með villuathugun.",
          "correct": false
        },
        {
          "title": "Ógilt svar"
        }
      ]
    }
  ]
}